odoo/addons/report_company_details_translatable/README.rst
odoo/addons/report_company_details_translatable/__init__.py
odoo/addons/report_company_details_translatable/__manifest__.py
odoo/addons/report_company_details_translatable/i18n/es.po
odoo/addons/report_company_details_translatable/i18n/it.po
odoo/addons/report_company_details_translatable/i18n/report_company_details_translatable.pot
odoo/addons/report_company_details_translatable/models/__init__.py
odoo/addons/report_company_details_translatable/models/res_company.py
odoo/addons/report_company_details_translatable/readme/DESCRIPTION.rst
odoo/addons/report_company_details_translatable/static/description/icon.png
odoo/addons/report_company_details_translatable/static/description/index.html
odoo_addon_report_company_details_translatable-16.0.1.0.0.8.dist-info/METADATA
odoo_addon_report_company_details_translatable-16.0.1.0.0.8.dist-info/WHEEL
odoo_addon_report_company_details_translatable-16.0.1.0.0.8.dist-info/top_level.txt
odoo_addon_report_company_details_translatable-16.0.1.0.0.8.dist-info/RECORD
